{
  "__type": "VoiceVoxNotes:#voxsay.Base.VoiceVox",
  "notes": [
    {
      "frame_length": 2,
      "key": null,
      "lyric": "",
      "notelen": "R"
    },
    {
      "frame_length": 46,
      "key": 60,
      "lyric": "ら",
      "notelen": "C4"
    },
    {
      "frame_length": 46,
      "key": 62,
      "lyric": "ら",
      "notelen": "D4"
    },
    {
      "frame_length": 46,
      "key": 64,
      "lyric": "ら",
      "notelen": "E4"
    },
    {
      "frame_length": 46,
      "key": 65,
      "lyric": "ら",
      "notelen": "F4"
    },
    {
      "frame_length": 46,
      "key": 67,
      "lyric": "ら",
      "notelen": "G4"
    },
    {
      "frame_length": 46,
      "key": 69,
      "lyric": "ら",
      "notelen": "A4"
    },
    {
      "frame_length": 46,
      "key": 71,
      "lyric": "ら",
      "notelen": "B4"
    },
    {
      "frame_length": 46,
      "key": 72,
      "lyric": "ら",
      "notelen": "C4"
    }
  ]
}